<annotation>
	<folder>Square_mA</folder>
	<filename>1606896007559.png</filename>
	<path>/home/orlando/PycharmProjects/ObjDetect/Square_mA/1606896007559.png</path>
	<source>
		<database>Unknown</database>
	</source>
	<size>
		<width>670</width>
		<height>365</height>
		<depth>3</depth>
	</size>
	<segmented>0</segmented>
	<object>
		<name>MilliAmp_Meter</name>
		<pose>Unspecified</pose>
		<truncated>0</truncated>
		<difficult>0</difficult>
		<bndbox>
			<xmin>149</xmin>
			<ymin>60</ymin>
			<xmax>445</xmax>
			<ymax>213</ymax>
		</bndbox>
	</object>
</annotation>
